{
    "code": 0,
    "msg": "succ",
    "data": {
        "teacher_list": [
            {
                "user_number": "877468828",
                "sex": 1,
                "display_name": "王家麦子",
                "sub_display_name": "王家麦子",
                "qreserve_sign": 0,
                "subject_name": "从前有座山山上有座庙从前有座山十七",
                "sub_subject_name": "钢管舞 · 水彩画",
                "domain": "#",
                "remain_time": 2,
                "avatar": "http://img.gsxservice.com/30518_j897m0no.jpeg@1e_58w_58h_1c_0i_1o_90Q_1x.jpeg"
            },
            {
                "user_number": "877468828",
                "sex": 0,
                "display_name": "小王老师",
                "sub_display_name": "王家麦子",
                "qreserve_sign": 1,
                "subject_name": "水彩画 · 钢管舞 · 山水画",
                "sub_subject_name": "钢管舞 · 水彩画",
                "domain": "#",
                "remain_time": 20,
                "avatar": "http://img.gsxservice.com/30518_j897m0no.jpeg@1e_58w_58h_1c_0i_1o_90Q_1x.jpeg"
            },
            {
                "user_number": "877468828",
                "sex": 1,
                "display_name": "小王老师",
                "sub_display_name": "王家麦子",
                "qreserve_sign": 1,
                "subject_name": "从前有座山山上有座庙从前有座山山上有座庙",
                "sub_subject_name": "水彩画 · 山水画 · 山水画",
                "domain": "#",
                "remain_time": 200,
                "avatar": "http://img.gsxservice.com/30518_j897m0no.jpeg@1e_58w_58h_1c_0i_1o_90Q_1x.jpeg"
            },
            {
                "user_number": "877468828",
                "sex": 0,
                "display_name": "小王老师",
                "sub_display_name": "王家麦子王家麦子",
                "qreserve_sign": 1,
                "subject_name": "水彩画 · 钢管舞 · 山水画",
                "sub_subject_name": "钢管舞 · 水彩画",
                "domain": "#",
                "remain_time": 200,
                "avatar": "http://img.gsxservice.com/30518_j897m0no.jpeg@1e_58w_58h_1c_0i_1o_90Q_1x.jpeg"
            },
            {
                "user_number": "877468828",
                "sex": 0,
                "display_name": "小王老师",
                "sub_display_name": "王家麦子",
                "qreserve_sign": 1,
                "subject_name": "水彩画 · 钢管舞 · 山水画",
                "sub_subject_name": "钢管舞 · 水彩画",
                "domain": "#",
                "remain_time": 0,
                "avatar": "http://img.gsxservice.com/30518_j897m0no.jpeg@1e_58w_58h_1c_0i_1o_90Q_1x.jpeg"
            },
            {
                "user_number": "877468828",
                "sex": 0,
                "display_name": "小王老师",
                "sub_display_name": "王家麦子",
                "qreserve_sign": 1,
                "subject_name": "水彩画 · 钢管舞 · 山水画",
                "sub_subject_name": "钢管舞 · 水彩画",
                "domain": "#",
                "remain_time": 20,
                "avatar": "http://img.gsxservice.com/30518_j897m0no.jpeg@1e_58w_58h_1c_0i_1o_90Q_1x.jpeg"
            },
            {
                "user_number": "877468828",
                "sex": 1,
                "display_name": "小王老师",
                "sub_display_name": "王家麦子",
                "qreserve_sign": 1,
                "subject_name": "从前有座山山上有座庙从前有座山山上有座庙",
                "sub_subject_name": "钢管舞 · 水彩画",
                "domain": "#",
                "remain_time": 200,
                "avatar": "http://img.gsxservice.com/30518_j897m0no.jpeg@1e_58w_58h_1c_0i_1o_90Q_1x.jpeg"
            },
            {
                "user_number": "877468828",
                "sex": 0,
                "display_name": "小王老师",
                "sub_display_name": "王家麦子王家麦子",
                "qreserve_sign": 1,
                "subject_name": "水彩画 · 钢管舞 · 山水画",
                "sub_subject_name": "钢管舞 · 水彩画",
                "domain": "#",
                "remain_time": 200,
                "avatar": "http://img.gsxservice.com/30518_j897m0no.jpeg@1e_58w_58h_1c_0i_1o_90Q_1x.jpeg"
            },
            {
                "user_number": "877468828",
                "sex": 0,
                "display_name": "小王老师",
                "sub_display_name": "王家麦子",
                "qreserve_sign": 1,
                "subject_name": "水彩画 · 钢管舞 · 山水画",
                "sub_subject_name": "钢管舞 · 水彩画",
                "domain": "#",
                "remain_time": 0,
                "avatar": "http://img.gsxservice.com/30518_j897m0no.jpeg@1e_58w_58h_1c_0i_1o_90Q_1x.jpeg"
            },
            {
                "user_number": "877468828",
                "sex": 0,
                "display_name": "小王老师",
                "sub_display_name": "王家麦子",
                "qreserve_sign": 1,
                "subject_name": "水彩画 · 钢管舞 · 山水画",
                "sub_subject_name": "钢管舞 · 水彩画",
                "domain": "#",
                "remain_time": 20,
                "avatar": "http://img.gsxservice.com/30518_j897m0no.jpeg@1e_58w_58h_1c_0i_1o_90Q_1x.jpeg"
            },
            {
                "user_number": "877468828",
                "sex": 1,
                "display_name": "小王老师",
                "sub_display_name": "王家麦子",
                "qreserve_sign": 1,
                "subject_name": "从前有座山山上有座庙从前有座山山上有座庙",
                "sub_subject_name": "钢管舞 · 水彩画",
                "domain": "#",
                "remain_time": 200,
                "avatar": "http://img.gsxservice.com/30518_j897m0no.jpeg@1e_58w_58h_1c_0i_1o_90Q_1x.jpeg"
            },
            {
                "user_number": "877468828",
                "sex": 0,
                "display_name": "小王老师",
                "sub_display_name": "王家麦子王家麦子",
                "qreserve_sign": 1,
                "subject_name": "水彩画 · 钢管舞 · 山水画",
                "sub_subject_name": "钢管舞 · 水彩画 · 山水画",
                "domain": "#",
                "remain_time": 200,
                "avatar": "http://img.gsxservice.com/30518_j897m0no.jpeg@1e_58w_58h_1c_0i_1o_90Q_1x.jpeg"
            },
            {
                "user_number": "877468828",
                "sex": 0,
                "display_name": "小王老师",
                "sub_display_name": "王家麦子",
                "qreserve_sign": 1,
                "subject_name": "水彩画 · 钢管舞 · 山水画",
                "sub_subject_name": "钢管舞 · 水彩画",
                "domain": "#",
                "remain_time": 0,
                "avatar": "http://img.gsxservice.com/30518_j897m0no.jpeg@1e_58w_58h_1c_0i_1o_90Q_1x.jpeg"
            }
        ]
    },
    "ts": 1425463432
}